{
  "cycle": 96,
  "version": "v2.36.0",
  "last_updated": "2026-06-20T00:00:00+00:00",
  "status": "OK",
  "overall_score": 0.95,
  "grade": "OK",
  "dimensions": {
    "structural": 0.92,
    "benchmark": 0.8174,
    "optimize_effect": 0.98,
    "coverage": 1.0,
    "absorption_potential": 1.0,
    "constitutional": 1.0
  },
  "edit_budget": {
    "allocated": 3,
    "consumed": 3,
    "remaining": 0,
    "next_cycle": 3,
    "notes": "cycle-96: 全面优化完成 — 合并重叠技能, 创建6个composite, 12个redirects, 净减少~3500行"
  },
  "next_actions": [
    "cycle-96: 6个composite创建完成 (github-workflow, creative-tools, mlops-toolchain, productivity-suite, social-monitor, paper-pipeline)",
    "cycle-96: 12个目录索引文件转为redirects",
    "cycle-96: 净减少~3500行代码, 197个SKILL.md全部通过YAML验证",
    "cycle-97: 清理冗余文件, 更新README和文档"
  ],
  "highlights": [
    "cycle-96: 全面优化完成 — 合并重叠技能, 创建6个composite, 12个redirects",
    "cycle-96: 净减少~3500行代码, 197个SKILL.md全部通过YAML验证"
  ]
}